{
  "countries": [
    {"name": "Afghanistan", "code": "AF"},
    {"name": "Australia", "code": "AU"},
    {"name": "Bangladesh", "code": "BD"},
    {"name": "Bhutan", "code": "BT"},
    {"name": "Brazil", "code": "BR"},
    {"name": "Canada", "code": "CA"},
    {"name": "China", "code": "CN"},
    {"name": "Egypt", "code": "EG"},
    {"name": "France", "code": "FR"},
    {"name": "Germany", "code": "DE"},
    {"name": "India", "code": "IN"},
    {"name": "Indonesia", "code": "ID"},
    {"name": "Iran", "code": "IR"},
    {"name": "Iraq", "code": "IQ"},
    {"name": "Japan", "code": "JP"},
    {"name": "Kenya", "code": "KE"},
    {"name": "Malaysia", "code": "MY"},
    {"name": "Maldives", "code": "MV"},
    {"name": "Mexico", "code": "MX"},
    {"name": "Myanmar", "code": "MM"},
    {"name": "Nepal", "code": "NP"},
    {"name": "New Zealand", "code": "NZ"},
    {"name": "Nigeria", "code": "NG"},
    {"name": "Oman", "code": "OM"},
    {"name": "Pakistan", "code": "PK"},
    {"name": "Philippines", "code": "PH"},
    {"name": "Qatar", "code": "QA"},
    {"name": "Russia", "code": "RU"},
    {"name": "Saudi Arabia", "code": "SA"},
    {"name": "Singapore", "code": "SG"},
    {"name": "South Africa", "code": "ZA"},
    {"name": "South Korea", "code": "KR"},
    {"name": "Spain", "code": "ES"},
    {"name": "Sri Lanka", "code": "LK"},
    {"name": "Thailand", "code": "TH"},
    {"name": "Turkey", "code": "TR"},
    {"name": "United Arab Emirates", "code": "AE"},
    {"name": "United Kingdom", "code": "GB"},
    {"name": "United States", "code": "US"},
    {"name": "Vietnam", "code": "VN"},
    {"name": "Italy", "code": "IT"},
    {"name": "Netherlands", "code": "NL"}
  ],
  "states": {
    "AF": [
      {"name": "Kabul", "cities": ["Kabul", "Paghman", "Chahar Asyab", "Bagrami", "Deh Sabz"]},
      {"name": "Kandahar", "cities": ["Kandahar", "Spin Boldak", "Daman", "Panjwai", "Arghandab"]},
      {"name": "Herat", "cities": ["Herat", "Islam Qala", "Guzara", "Injil", "Zindajan"]},
      {"name": "Balkh", "cities": ["Mazar-i-Sharif", "Balkh", "Dehdadi", "Nahri Shahi", "Chimtal"]},
      {"name": "Nangarhar", "cities": ["Jalalabad", "Behsud", "Surkhrud", "Kama", "Rodat"]},
      {"name": "Kunduz", "cities": ["Kunduz", "Imam Sahib", "Khanabad", "Aliabad", "Chahar Dara"]},
      {"name": "Baghlan", "cities": ["Pul-e-Khumri", "Baghlan", "Doshi", "Nahrin", "Andarab"]},
      {"name": "Ghazni", "cities": ["Ghazni", "Jaghori", "Qarabagh", "Malistan", "Jaghatu"]},
      {"name": "Badakhshan", "cities": ["Fayzabad", "Jurm", "Baharak", "Kishim", "Ishkashim"]}
    ],
    "AU": [
      {"name": "New South Wales", "cities": ["Sydney", "Newcastle", "Wollongong", "Central Coast", "Maitland", "Coffs Harbour", "Wagga Wagga", "Port Macquarie", "Tamworth", "Orange", "Dubbo", "Bathurst", "Albury", "Lismore", "Broken Hill"]},
      {"name": "Victoria", "cities": ["Melbourne", "Geelong", "Ballarat", "Bendigo", "Shepparton", "Mildura", "Warrnambool", "Wodonga", "Traralgon", "Wangaratta", "Sunbury", "Melton", "Frankston"]},
      {"name": "Queensland", "cities": ["Brisbane", "Gold Coast", "Sunshine Coast", "Townsville", "Cairns", "Toowoomba", "Mackay", "Rockhampton", "Bundaberg", "Hervey Bay", "Gladstone", "Mount Isa"]},
      {"name": "Western Australia", "cities": ["Perth", "Fremantle", "Mandurah", "Bunbury", "Geraldton", "Kalgoorlie", "Albany", "Broome", "Karratha", "Port Hedland"]},
      {"name": "South Australia", "cities": ["Adelaide", "Mount Gambier", "Whyalla", "Murray Bridge", "Port Augusta", "Port Pirie", "Port Lincoln", "Victor Harbor"]},
      {"name": "Tasmania", "cities": ["Hobart", "Launceston", "Devonport", "Burnie", "Kingston", "Ulverstone"]},
      {"name": "Northern Territory", "cities": ["Darwin", "Alice Springs", "Katherine", "Palmerston", "Tennant Creek"]},
      {"name": "Australian Capital Territory", "cities": ["Canberra", "Queanbeyan"]}
    ],
    "BD": [
      {"name": "Dhaka Division", "cities": ["Dhaka", "Narayanganj", "Gazipur", "Tangail", "Kishoreganj", "Manikganj", "Munshiganj", "Narsingdi", "Faridpur", "Madaripur", "Gopalganj", "Rajbari", "Shariatpur"]},
      {"name": "Chittagong Division", "cities": ["Chittagong", "Comilla", "Brahmanbaria", "Chandpur", "Lakshmipur", "Noakhali", "Feni", "Khagrachhari", "Rangamati", "Bandarban", "Cox's Bazar"]},
      {"name": "Rajshahi Division", "cities": ["Rajshahi", "Bogra", "Pabna", "Sirajganj", "Natore", "Nawabganj", "Naogaon", "Joypurhat"]},
      {"name": "Khulna Division", "cities": ["Khulna", "Jessore", "Satkhira", "Bagerhat", "Narail", "Magura", "Jhenaidah", "Chuadanga", "Kushtia", "Meherpur"]},
      {"name": "Barisal Division", "cities": ["Barisal", "Bhola", "Patuakhali", "Pirojpur", "Jhalokati", "Barguna"]},
      {"name": "Sylhet Division", "cities": ["Sylhet", "Moulvibazar", "Habiganj", "Sunamganj"]},
      {"name": "Rangpur Division", "cities": ["Rangpur", "Dinajpur", "Kurigram", "Lalmonirhat", "Nilphamari", "Gaibandha", "Thakurgaon", "Panchagarh"]},
      {"name": "Mymensingh Division", "cities": ["Mymensingh", "Jamalpur", "Sherpur", "Netrokona"]}
    ],
    "BT": [
      {"name": "Thimphu", "cities": ["Thimphu", "Babesa", "Changzamtog", "Motithang"]},
      {"name": "Paro", "cities": ["Paro", "Shaba", "Doteng", "Bondey"]},
      {"name": "Punakha", "cities": ["Punakha", "Khuruthang", "Kabesa"]},
      {"name": "Wangdue Phodrang", "cities": ["Bajo", "Gaselo", "Rubesa"]},
      {"name": "Bumthang", "cities": ["Jakar", "Chamkhar", "Ura"]},
      {"name": "Trongsa", "cities": ["Trongsa"]},
      {"name": "Mongar", "cities": ["Mongar", "Gyalpozhing"]},
      {"name": "Trashigang", "cities": ["Trashigang", "Rangjung", "Kanglung"]},
      {"name": "Samtse", "cities": ["Samtse", "Gomtu"]},
      {"name": "Phuentsholing", "cities": ["Phuentsholing", "Gedu"]}
    ],
    "BR": [
      {"name": "São Paulo", "cities": ["São Paulo", "Guarulhos", "Campinas", "São Bernardo do Campo", "Santo André", "Osasco", "Sorocaba", "Ribeirão Preto", "Santos", "São José dos Campos", "Jundiaí", "Piracicaba", "Bauru", "Limeira", "Franca"]},
      {"name": "Rio de Janeiro", "cities": ["Rio de Janeiro", "Niterói", "Nova Iguaçu", "Duque de Caxias", "São Gonçalo", "Petrópolis", "Volta Redonda", "Campos dos Goytacazes", "Macaé", "Cabo Frio"]},
      {"name": "Minas Gerais", "cities": ["Belo Horizonte", "Uberlândia", "Contagem", "Juiz de Fora", "Betim", "Montes Claros", "Ribeirão das Neves", "Uberaba", "Governador Valadares", "Ipatinga"]},
      {"name": "Bahia", "cities": ["Salvador", "Feira de Santana", "Vitória da Conquista", "Camaçari", "Itabuna", "Juazeiro", "Ilhéus", "Lauro de Freitas"]},
      {"name": "Rio Grande do Sul", "cities": ["Porto Alegre", "Caxias do Sul", "Pelotas", "Canoas", "Santa Maria", "Gravataí", "Viamão", "Novo Hamburgo"]},
      {"name": "Paraná", "cities": ["Curitiba", "Londrina", "Maringá", "Ponta Grossa", "Cascavel", "São José dos Pinhais", "Foz do Iguaçu", "Colombo"]},
      {"name": "Pernambuco", "cities": ["Recife", "Jaboatão dos Guararapes", "Olinda", "Caruaru", "Petrolina", "Paulista", "Cabo de Santo Agostinho"]},
      {"name": "Ceará", "cities": ["Fortaleza", "Caucaia", "Juazeiro do Norte", "Maracanaú", "Sobral", "Crato", "Itapipoca"]},
      {"name": "Pará", "cities": ["Belém", "Ananindeua", "Santarém", "Marabá", "Castanhal", "Parauapebas"]},
      {"name": "Santa Catarina", "cities": ["Florianópolis", "Joinville", "Blumenau", "São José", "Criciúma", "Chapecó", "Itajaí"]},
      {"name": "Goiás", "cities": ["Goiânia", "Aparecida de Goiânia", "Anápolis", "Rio Verde", "Luziânia"]},
      {"name": "Maranhão", "cities": ["São Luís", "Imperatriz", "São José de Ribamar", "Timon", "Caxias"]},
      {"name": "Amazonas", "cities": ["Manaus", "Parintins", "Itacoatiara", "Manacapuru", "Coari"]}
    ],
    "CA": [
      {"name": "Ontario", "cities": ["Toronto", "Ottawa", "Mississauga", "Brampton", "Hamilton", "London", "Markham", "Vaughan", "Kitchener", "Windsor", "Richmond Hill", "Oakville", "Burlington", "Oshawa", "Barrie", "St. Catharines", "Cambridge", "Kingston", "Guelph", "Thunder Bay"]},
      {"name": "Quebec", "cities": ["Montreal", "Quebec City", "Laval", "Gatineau", "Longueuil", "Sherbrooke", "Saguenay", "Lévis", "Trois-Rivières", "Terrebonne", "Saint-Jean-sur-Richelieu", "Brossard", "Drummondville"]},
      {"name": "British Columbia", "cities": ["Vancouver", "Surrey", "Burnaby", "Richmond", "Coquitlam", "Kelowna", "Victoria", "Abbotsford", "Nanaimo", "Kamloops", "Chilliwack", "Prince George", "Vernon"]},
      {"name": "Alberta", "cities": ["Calgary", "Edmonton", "Red Deer", "Lethbridge", "St. Albert", "Medicine Hat", "Grande Prairie", "Airdrie", "Spruce Grove", "Fort McMurray"]},
      {"name": "Manitoba", "cities": ["Winnipeg", "Brandon", "Steinbach", "Thompson", "Portage la Prairie", "Selkirk", "Winkler"]},
      {"name": "Saskatchewan", "cities": ["Saskatoon", "Regina", "Prince Albert", "Moose Jaw", "Swift Current", "Yorkton", "North Battleford"]},
      {"name": "Nova Scotia", "cities": ["Halifax", "Dartmouth", "Sydney", "Truro", "New Glasgow", "Glace Bay"]},
      {"name": "New Brunswick", "cities": ["Saint John", "Moncton", "Fredericton", "Dieppe", "Miramichi", "Edmundston"]},
      {"name": "Newfoundland and Labrador", "cities": ["St. John's", "Mount Pearl", "Corner Brook", "Conception Bay South", "Paradise"]},
      {"name": "Prince Edward Island", "cities": ["Charlottetown", "Summerside", "Stratford"]},
      {"name": "Northwest Territories", "cities": ["Yellowknife", "Hay River", "Inuvik"]},
      {"name": "Yukon", "cities": ["Whitehorse", "Dawson City"]},
      {"name": "Nunavut", "cities": ["Iqaluit", "Rankin Inlet", "Arviat"]}
    ],
    "CN": [
      {"name": "Beijing", "cities": ["Beijing", "Chaoyang", "Haidian", "Fengtai", "Shijingshan", "Tongzhou", "Shunyi", "Daxing"]},
      {"name": "Shanghai", "cities": ["Shanghai", "Pudong", "Huangpu", "Xuhui", "Changning", "Jingan", "Putuo", "Hongkou", "Yangpu", "Minhang", "Baoshan", "Jiading", "Songjiang"]},
      {"name": "Guangdong", "cities": ["Guangzhou", "Shenzhen", "Dongguan", "Foshan", "Zhongshan", "Zhuhai", "Huizhou", "Jiangmen", "Shantou", "Zhanjiang", "Maoming", "Zhaoqing"]},
      {"name": "Zhejiang", "cities": ["Hangzhou", "Ningbo", "Wenzhou", "Shaoxing", "Jiaxing", "Huzhou", "Jinhua", "Taizhou", "Quzhou", "Lishui"]},
      {"name": "Jiangsu", "cities": ["Nanjing", "Suzhou", "Wuxi", "Changzhou", "Nantong", "Yangzhou", "Xuzhou", "Zhenjiang", "Yancheng", "Taizhou", "Lianyungang"]},
      {"name": "Shandong", "cities": ["Jinan", "Qingdao", "Yantai", "Weifang", "Zibo", "Weihai", "Linyi", "Jining", "Zaozhuang", "Tai'an", "Dongying"]},
      {"name": "Sichuan", "cities": ["Chengdu", "Mianyang", "Leshan", "Nanchong", "Yibin", "Luzhou", "Deyang", "Zigong", "Panzhihua", "Suining"]},
      {"name": "Hubei", "cities": ["Wuhan", "Yichang", "Xiangyang", "Jingzhou", "Huangshi", "Shiyan", "Xiaogan", "Huanggang", "Ezhou"]},
      {"name": "Hunan", "cities": ["Changsha", "Zhuzhou", "Xiangtan", "Hengyang", "Yueyang", "Changde", "Chenzhou", "Yongzhou", "Loudi"]},
      {"name": "Henan", "cities": ["Zhengzhou", "Luoyang", "Kaifeng", "Nanyang", "Xinxiang", "Anyang", "Shangqiu", "Pingdingshan", "Xuchang"]},
      {"name": "Hebei", "cities": ["Shijiazhuang", "Tangshan", "Baoding", "Langfang", "Qinhuangdao", "Handan", "Cangzhou", "Xingtai", "Hengshui"]},
      {"name": "Fujian", "cities": ["Fuzhou", "Xiamen", "Quanzhou", "Zhangzhou", "Putian", "Longyan", "Sanming", "Nanping"]},
      {"name": "Liaoning", "cities": ["Shenyang", "Dalian", "Anshan", "Fushun", "Benxi", "Dandong", "Jinzhou", "Yingkou", "Liaoyang"]},
      {"name": "Shaanxi", "cities": ["Xi'an", "Xianyang", "Baoji", "Weinan", "Yan'an", "Hanzhong", "Yulin", "Ankang"]},
      {"name": "Tianjin", "cities": ["Tianjin", "Binhai", "Dongli", "Xiqing", "Beichen", "Jinnan"]},
      {"name": "Chongqing", "cities": ["Chongqing", "Wanzhou", "Fuling", "Yubei", "Jiulongpo", "Shapingba"]}
    ],
    "EG": [
      {"name": "Cairo", "cities": ["Cairo", "Heliopolis", "Nasr City", "Maadi", "New Cairo", "Shubra El Kheima"]},
      {"name": "Alexandria", "cities": ["Alexandria", "Borg El Arab", "Abu Qir", "Montaza"]},
      {"name": "Giza", "cities": ["Giza", "6th of October City", "Sheikh Zayed", "El Haram", "Dokki", "Mohandessin"]},
      {"name": "Qalyubia", "cities": ["Banha", "Qalyub", "Shubra El Kheima", "El Khanka", "Qaha"]},
      {"name": "Port Said", "cities": ["Port Said"]},
      {"name": "Suez", "cities": ["Suez"]},
      {"name": "Luxor", "cities": ["Luxor", "Karnak", "El Tod"]},
      {"name": "Aswan", "cities": ["Aswan", "Kom Ombo", "Edfu"]},
      {"name": "Asyut", "cities": ["Asyut", "Manfalut", "Abu Tig"]},
      {"name": "Sohag", "cities": ["Sohag", "Girga", "Akhmim"]},
      {"name": "Dakahlia", "cities": ["Mansoura", "Talkha", "Mit Ghamr", "El Senbellawein"]},
      {"name": "Sharqia", "cities": ["Zagazig", "10th of Ramadan City", "Bilbeis", "Abu Hammad"]},
      {"name": "Red Sea", "cities": ["Hurghada", "Safaga", "El Gouna", "Marsa Alam"]},
      {"name": "South Sinai", "cities": ["Sharm El Sheikh", "Dahab", "Taba", "Nuweiba"]}
    ],
    "FR": [
      {"name": "Île-de-France", "cities": ["Paris", "Boulogne-Billancourt", "Saint-Denis", "Argenteuil", "Montreuil", "Nanterre", "Créteil", "Versailles", "Courbevoie", "Vitry-sur-Seine", "Colombes", "Asnières-sur-Seine"]},
      {"name": "Provence-Alpes-Côte d'Azur", "cities": ["Marseille", "Nice", "Toulon", "Aix-en-Provence", "Avignon", "Antibes", "Cannes", "Fréjus", "Hyères", "Arles"]},
      {"name": "Auvergne-Rhône-Alpes", "cities": ["Lyon", "Saint-Étienne", "Grenoble", "Villeurbanne", "Clermont-Ferrand", "Annecy", "Chambéry", "Valence", "Bourg-en-Bresse"]},
      {"name": "Nouvelle-Aquitaine", "cities": ["Bordeaux", "Limoges", "Poitiers", "Mérignac", "Pau", "La Rochelle", "Angoulême", "Bayonne", "Pessac"]},
      {"name": "Occitanie", "cities": ["Toulouse", "Montpellier", "Nîmes", "Perpignan", "Béziers", "Narbonne", "Albi", "Tarbes", "Carcassonne"]},
      {"name": "Hauts-de-France", "cities": ["Lille", "Amiens", "Roubaix", "Tourcoing", "Dunkerque", "Calais", "Valenciennes", "Boulogne-sur-Mer", "Lens"]},
      {"name": "Grand Est", "cities": ["Strasbourg", "Reims", "Metz", "Mulhouse", "Nancy", "Troyes", "Colmar", "Charleville-Mézières"]},
      {"name": "Pays de la Loire", "cities": ["Nantes", "Angers", "Le Mans", "Saint-Nazaire", "La Roche-sur-Yon", "Cholet", "Laval", "Saumur"]},
      {"name": "Bretagne", "cities": ["Rennes", "Brest", "Quimper", "Lorient", "Vannes", "Saint-Malo", "Saint-Brieuc", "Morlaix"]},
      {"name": "Normandie", "cities": ["Rouen", "Le Havre", "Caen", "Cherbourg", "Évreux", "Dieppe", "Lisieux"]}
    ],
    "DE": [
      {"name": "Bavaria", "cities": ["Munich", "Nuremberg", "Augsburg", "Regensburg", "Ingolstadt", "Würzburg", "Fürth", "Erlangen", "Bamberg", "Bayreuth", "Landshut", "Passau", "Rosenheim"]},
      {"name": "North Rhine-Westphalia", "cities": ["Cologne", "Düsseldorf", "Dortmund", "Essen", "Duisburg", "Bochum", "Wuppertal", "Bielefeld", "Bonn", "Münster", "Gelsenkirchen", "Mönchengladbach", "Aachen"]},
      {"name": "Baden-Württemberg", "cities": ["Stuttgart", "Karlsruhe", "Mannheim", "Freiburg", "Heidelberg", "Ulm", "Heilbronn", "Pforzheim", "Reutlingen", "Tübingen", "Konstanz"]},
      {"name": "Lower Saxony", "cities": ["Hanover", "Braunschweig", "Oldenburg", "Osnabrück", "Wolfsburg", "Göttingen", "Salzgitter", "Hildesheim", "Wilhelmshaven", "Lüneburg"]},
      {"name": "Hesse", "cities": ["Frankfurt", "Wiesbaden", "Kassel", "Darmstadt", "Offenbach", "Marburg", "Fulda", "Gießen", "Hanau"]},
      {"name": "Saxony", "cities": ["Leipzig", "Dresden", "Chemnitz", "Zwickau", "Plauen", "Görlitz", "Freiberg", "Bautzen"]},
      {"name": "Berlin", "cities": ["Berlin", "Charlottenburg", "Kreuzberg", "Neukölln", "Spandau", "Steglitz", "Tempelhof", "Pankow", "Mitte"]},
      {"name": "Hamburg", "cities": ["Hamburg", "Altona", "Bergedorf", "Harburg", "Wandsbek", "Eimsbüttel"]},
      {"name": "Schleswig-Holstein", "cities": ["Kiel", "Lübeck", "Flensburg", "Neumünster", "Norderstedt", "Elmshorn"]},
      {"name": "Rhineland-Palatinate", "cities": ["Mainz", "Ludwigshafen", "Koblenz", "Trier", "Kaiserslautern", "Worms", "Neuwied"]},
      {"name": "Brandenburg", "cities": ["Potsdam", "Cottbus", "Brandenburg an der Havel", "Frankfurt (Oder)", "Oranienburg"]},
      {"name": "Saxony-Anhalt", "cities": ["Magdeburg", "Halle", "Dessau-Roßlau", "Lutherstadt Wittenberg", "Stendal"]},
      {"name": "Thuringia", "cities": ["Erfurt", "Jena", "Gera", "Weimar", "Gotha", "Eisenach"]},
      {"name": "Mecklenburg-Vorpommern", "cities": ["Rostock", "Schwerin", "Neubrandenburg", "Stralsund", "Greifswald"]},
      {"name": "Saarland", "cities": ["Saarbrücken", "Neunkirchen", "Völklingen", "Homburg"]},
      {"name": "Bremen", "cities": ["Bremen", "Bremerhaven"]}
    ],
    "IN": [
      {"name": "Maharashtra", "cities": ["Mumbai", "Pune", "Nagpur", "Thane", "Nashik", "Aurangabad", "Solapur", "Kolhapur", "Amravati", "Navi Mumbai", "Sangli", "Jalgaon", "Akola", "Latur", "Dhule", "Ahmednagar", "Chandrapur", "Parbhani", "Jalna"]},
      {"name": "Delhi", "cities": ["New Delhi", "Delhi", "Dwarka", "Rohini", "Saket", "Janakpuri", "Karol Bagh", "Lajpat Nagar", "Connaught Place", "Greater Kailash"]},
      {"name": "Karnataka", "cities": ["Bangalore", "Mysore", "Hubli", "Mangalore", "Belgaum", "Gulbarga", "Davangere", "Bellary", "Shimoga", "Tumkur", "Raichur", "Bijapur", "Hospet", "Udupi"]},
      {"name": "Tamil Nadu", "cities": ["Chennai", "Coimbatore", "Madurai", "Tiruchirappalli", "Salem", "Tirunelveli", "Tiruppur", "Erode", "Vellore", "Thoothukudi", "Dindigul", "Thanjavur", "Ranipet", "Sivakasi"]},
      {"name": "Gujarat", "cities": ["Ahmedabad", "Surat", "Vadodara", "Rajkot", "Bhavnagar", "Jamnagar", "Junagadh", "Gandhinagar", "Anand", "Morbi", "Nadiad", "Mehsana", "Bharuch", "Navsari"]},
      {"name": "West Bengal", "cities": ["Kolkata", "Howrah", "Durgapur", "Asansol", "Siliguri", "Bardhaman", "Malda", "Baharampur", "Habra", "Kharagpur", "Shantipur", "Balurghat", "Krishnanagar"]},
      {"name": "Telangana", "cities": ["Hyderabad", "Warangal", "Nizamabad", "Karimnagar", "Khammam", "Ramagundam", "Mahbubnagar", "Nalgonda", "Adilabad", "Suryapet", "Siddipet"]},
      {"name": "Rajasthan", "cities": ["Jaipur", "Jodhpur", "Udaipur", "Kota", "Bikaner", "Ajmer", "Bhilwara", "Alwar", "Sikar", "Pali", "Sri Ganganagar", "Bharatpur", "Chittorgarh"]},
      {"name": "Uttar Pradesh", "cities": ["Lucknow", "Kanpur", "Ghaziabad", "Agra", "Varanasi", "Meerut", "Prayagraj", "Bareilly", "Aligarh", "Moradabad", "Saharanpur", "Gorakhpur", "Noida", "Firozabad", "Jhansi", "Muzaffarnagar", "Mathura", "Rampur"]},
      {"name": "Madhya Pradesh", "cities": ["Indore", "Bhopal", "Jabalpur", "Gwalior", "Ujjain", "Sagar", "Dewas", "Satna", "Ratlam", "Rewa", "Murwara", "Singrauli", "Burhanpur"]},
      {"name": "Bihar", "cities": ["Patna", "Gaya", "Bhagalpur", "Muzaffarpur", "Purnia", "Darbhanga", "Bihar Sharif", "Arrah", "Begusarai", "Katihar", "Munger", "Chhapra", "Bettiah"]},
      {"name": "Andhra Pradesh", "cities": ["Visakhapatnam", "Vijayawada", "Guntur", "Nellore", "Kurnool", "Rajahmundry", "Tirupati", "Kakinada", "Kadapa", "Anantapur", "Vizianagaram", "Eluru", "Ongole"]},
      {"name": "Kerala", "cities": ["Thiruvananthapuram", "Kochi", "Kozhikode", "Thrissur", "Kollam", "Kannur", "Alappuzha", "Palakkad", "Malappuram", "Kottayam", "Kasaragod"]},
      {"name": "Punjab", "cities": ["Ludhiana", "Amritsar", "Jalandhar", "Patiala", "Bathinda", "Mohali", "Pathankot", "Hoshiarpur", "Batala", "Moga", "Firozpur"]},
      {"name": "Haryana", "cities": ["Faridabad", "Gurugram", "Panipat", "Ambala", "Yamunanagar", "Rohtak", "Hisar", "Karnal", "Sonipat", "Panchkula", "Bhiwani", "Sirsa", "Jind"]},
      {"name": "Odisha", "cities": ["Bhubaneswar", "Cuttack", "Rourkela", "Brahmapur", "Sambalpur", "Puri", "Balasore", "Baripada", "Bhadrak", "Jharsuguda"]},
      {"name": "Assam", "cities": ["Guwahati", "Silchar", "Dibrugarh", "Jorhat", "Nagaon", "Tinsukia", "Tezpur", "Bongaigaon", "Karimganj"]},
      {"name": "Jharkhand", "cities": ["Ranchi", "Jamshedpur", "Dhanbad", "Bokaro", "Hazaribagh", "Deoghar", "Giridih", "Ramgarh", "Phusro"]},
      {"name": "Chhattisgarh", "cities": ["Raipur", "Bhilai", "Bilaspur", "Korba", "Durg", "Rajnandgaon", "Raigarh", "Jagdalpur", "Ambikapur"]},
      {"name": "Uttarakhand", "cities": ["Dehradun", "Haridwar", "Roorkee", "Haldwani", "Rudrapur", "Kashipur", "Rishikesh", "Kotdwar"]},
      {"name": "Himachal Pradesh", "cities": ["Shimla", "Dharamshala", "Solan", "Mandi", "Kullu", "Manali", "Hamirpur", "Una"]},
      {"name": "Goa", "cities": ["Panaji", "Margao", "Vasco da Gama", "Mapusa", "Ponda"]},
      {"name": "Jammu and Kashmir", "cities": ["Srinagar", "Jammu", "Anantnag", "Baramulla", "Sopore", "Pulwama", "Udhampur", "Kathua"]},
      {"name": "Chandigarh", "cities": ["Chandigarh", "Manimajra", "Mohali", "Panchkula"]},
      {"name": "Puducherry", "cities": ["Puducherry", "Karaikal", "Yanam", "Mahe"]},
      {"name": "Tripura", "cities": ["Agartala", "Dharmanagar", "Udaipur", "Kailasahar"]},
      {"name": "Meghalaya", "cities": ["Shillong", "Tura", "Jowai", "Nongstoin"]},
      {"name": "Manipur", "cities": ["Imphal", "Thoubal", "Kakching", "Bishnupur"]},
      {"name": "Nagaland", "cities": ["Kohima", "Dimapur", "Mokokchung", "Tuensang"]},
      {"name": "Arunachal Pradesh", "cities": ["Itanagar", "Naharlagun", "Pasighat", "Tawang"]},
      {"name": "Mizoram", "cities": ["Aizawl", "Lunglei", "Saiha", "Champhai"]},
      {"name": "Sikkim", "cities": ["Gangtok", "Namchi", "Gyalshing", "Mangan"]}
    ],
    "ID": [
      {"name": "Jakarta", "cities": ["Jakarta", "Central Jakarta", "North Jakarta", "South Jakarta", "East Jakarta", "West Jakarta"]},
      {"name": "West Java", "cities": ["Bandung", "Bekasi", "Depok", "Bogor", "Cirebon", "Tasikmalaya", "Sukabumi", "Karawang", "Subang"]},
      {"name": "East Java", "cities": ["Surabaya", "Malang", "Sidoarjo", "Kediri", "Jember", "Pasuruan", "Mojokerto", "Madiun", "Blitar", "Probolinggo"]},
      {"name": "Central Java", "cities": ["Semarang", "Surakarta", "Magelang", "Salatiga", "Pekalongan", "Tegal", "Kudus", "Cilacap", "Purwokerto"]},
      {"name": "Banten", "cities": ["Tangerang", "South Tangerang", "Serang", "Cilegon", "Pandeglang"]},
      {"name": "North Sumatra", "cities": ["Medan", "Binjai", "Pematang Siantar", "Tebing Tinggi", "Padang Sidempuan", "Tanjung Balai", "Kisaran"]},
      {"name": "South Sumatra", "cities": ["Palembang", "Lubuklinggau", "Prabumulih", "Pagar Alam", "Lahat"]},
      {"name": "West Sumatra", "cities": ["Padang", "Bukittinggi", "Payakumbuh", "Solok", "Sawahlunto"]},
      {"name": "Riau", "cities": ["Pekanbaru", "Dumai", "Bengkalis", "Duri"]},
      {"name": "South Sulawesi", "cities": ["Makassar", "Parepare", "Palopo", "Maros", "Bone"]},
      {"name": "Bali", "cities": ["Denpasar", "Singaraja", "Ubud", "Kuta", "Sanur", "Seminyak", "Gianyar", "Tabanan"]},
      {"name": "East Kalimantan", "cities": ["Samarinda", "Balikpapan", "Bontang", "Tenggarong"]},
      {"name": "West Kalimantan", "cities": ["Pontianak", "Singkawang", "Mempawah", "Sambas"]},
      {"name": "Yogyakarta", "cities": ["Yogyakarta", "Sleman", "Bantul", "Wonosari"]}
    ],
    "IR": [
      {"name": "Tehran", "cities": ["Tehran", "Karaj", "Varamin", "Eslamshahr", "Shahr-e Qods", "Robat Karim", "Qarchak"]},
      {"name": "Isfahan", "cities": ["Isfahan", "Kashan", "Najafabad", "Shahin Shahr", "Khomeynishahr", "Falavarjan"]},
      {"name": "Khorasan Razavi", "cities": ["Mashhad", "Neyshabur", "Sabzevar", "Torbat-e Heydarieh", "Kashmar", "Quchan"]},
      {"name": "Fars", "cities": ["Shiraz", "Marvdasht", "Jahrom", "Fasa", "Kazerun", "Lar"]},
      {"name": "East Azerbaijan", "cities": ["Tabriz", "Maragheh", "Marand", "Ahar", "Bonab", "Sarab"]},
      {"name": "Khuzestan", "cities": ["Ahvaz", "Dezful", "Abadan", "Khorramshahr", "Andimeshk", "Shush"]},
      {"name": "Mazandaran", "cities": ["Sari", "Babol", "Amol", "Qaemshahr", "Nowshahr", "Chalus"]},
      {"name": "Kerman", "cities": ["Kerman", "Rafsanjan", "Jiroft", "Sirjan", "Bam", "Zarand"]},
      {"name": "Alborz", "cities": ["Karaj", "Fardis", "Nazarabad", "Savojbolagh"]},
      {"name": "Gilan", "cities": ["Rasht", "Anzali", "Lahijan", "Langarud", "Rudsar", "Astara"]},
      {"name": "Qom", "cities": ["Qom"]},
      {"name": "West Azerbaijan", "cities": ["Urmia", "Khoy", "Miandoab", "Maku", "Salmas"]}
    ],
    "IQ": [
      {"name": "Baghdad", "cities": ["Baghdad", "Kadhimiya", "Sadr City", "Adhamiyah", "Karkh"]},
      {"name": "Basra", "cities": ["Basra", "Abu Al-Khaseeb", "Zubair", "Fao", "Qurna"]},
      {"name": "Erbil", "cities": ["Erbil", "Koya", "Soran", "Shaqlawa", "Rawanduz"]},
      {"name": "Sulaymaniyah", "cities": ["Sulaymaniyah", "Halabja", "Rania", "Penjwin", "Chamchamal"]},
      {"name": "Nineveh", "cities": ["Mosul", "Tal Afar", "Sinjar", "Hamdaniya", "Ba'shiqa"]},
      {"name": "Duhok", "cities": ["Duhok", "Zakho", "Amedi", "Akre", "Semel"]},
      {"name": "Najaf", "cities": ["Najaf", "Kufa", "Manathera"]},
      {"name": "Karbala", "cities": ["Karbala", "Hindiya"]},
      {"name": "Kirkuk", "cities": ["Kirkuk", "Hawija", "Daquq"]},
      {"name": "Diyala", "cities": ["Baqubah", "Muqdadiyah", "Khanaqin", "Balad Ruz"]}
    ],
    "JP": [
      {"name": "Tokyo", "cities": ["Tokyo", "Shibuya", "Shinjuku", "Minato", "Setagaya", "Hachioji", "Machida", "Tachikawa", "Fuchu", "Chofu", "Koto", "Edogawa", "Sumida", "Toshima"]},
      {"name": "Osaka", "cities": ["Osaka", "Sakai", "Higashiosaka", "Toyonaka", "Suita", "Hirakata", "Takatsuki", "Neyagawa", "Kishiwada", "Ibaraki"]},
      {"name": "Kanagawa", "cities": ["Yokohama", "Kawasaki", "Sagamihara", "Fujisawa", "Yokosuka", "Chigasaki", "Hiratsuka", "Atsugi", "Kamakura", "Odawara"]},
      {"name": "Aichi", "cities": ["Nagoya", "Toyota", "Okazaki", "Ichinomiya", "Kasugai", "Toyohashi", "Anjo", "Nishio", "Kariya", "Inazawa"]},
      {"name": "Hokkaido", "cities": ["Sapporo", "Asahikawa", "Hakodate", "Kushiro", "Obihiro", "Tomakomai", "Otaru", "Kitami", "Ebetsu", "Muroran"]},
      {"name": "Fukuoka", "cities": ["Fukuoka", "Kitakyushu", "Kurume", "Omuta", "Iizuka", "Kasuga", "Ōnojō", "Chikushino", "Munakata"]},
      {"name": "Hyogo", "cities": ["Kobe", "Himeji", "Amagasaki", "Nishinomiya", "Akashi", "Kakogawa", "Takarazuka", "Itami", "Kawanishi"]},
      {"name": "Saitama", "cities": ["Saitama", "Kawaguchi", "Kawagoe", "Koshigaya", "Tokorozawa", "Kasukabe", "Soka", "Ageo", "Kumagaya"]},
      {"name": "Chiba", "cities": ["Chiba", "Funabashi", "Matsudo", "Ichikawa", "Kashiwa", "Ichihara", "Urayasu", "Narita", "Kisarazu"]},
      {"name": "Kyoto", "cities": ["Kyoto", "Uji", "Kameoka", "Nagaokakyo", "Joyo", "Maizuru", "Fukuchiyama", "Muko"]},
      {"name": "Hiroshima", "cities": ["Hiroshima", "Fukuyama", "Kure", "Higashihiroshima", "Onomichi", "Hatsukaichi", "Mihara"]},
      {"name": "Shizuoka", "cities": ["Shizuoka", "Hamamatsu", "Numazu", "Fuji", "Iwata", "Yaizu", "Fujieda", "Mishima"]},
      {"name": "Miyagi", "cities": ["Sendai", "Ishinomaki", "Shiogama", "Kesennuma", "Natori", "Tagajo", "Iwanuma"]},
      {"name": "Niigata", "cities": ["Niigata", "Nagaoka", "Joetsu", "Sanjo", "Kashiwazaki", "Shibata"]}
    ],
    "KE": [
      {"name": "Nairobi", "cities": ["Nairobi", "Westlands", "Kasarani", "Embakasi", "Langata", "Kibra"]},
      {"name": "Mombasa", "cities": ["Mombasa", "Likoni", "Kisauni", "Changamwe", "Mvita", "Nyali"]},
      {"name": "Nakuru", "cities": ["Nakuru", "Naivasha", "Gilgil", "Molo", "Njoro"]},
      {"name": "Kiambu", "cities": ["Kiambu", "Thika", "Ruiru", "Kikuyu", "Limuru", "Gatundu"]},
      {"name": "Kisumu", "cities": ["Kisumu", "Ahero", "Maseno", "Muhoroni"]},
      {"name": "Uasin Gishu", "cities": ["Eldoret", "Burnt Forest", "Turbo", "Moiben"]},
      {"name": "Machakos", "cities": ["Machakos", "Athi River", "Kangundo", "Matuu", "Masii"]},
      {"name": "Kajiado", "cities": ["Kajiado", "Ngong", "Kitengela", "Ongata Rongai", "Namanga"]},
      {"name": "Nyeri", "cities": ["Nyeri", "Karatina", "Othaya", "Mukurweini", "Narumoru"]},
      {"name": "Meru", "cities": ["Meru", "Maua", "Nkubu", "Chuka", "Timau"]},
      {"name": "Kilifi", "cities": ["Kilifi", "Malindi", "Watamu", "Mtwapa", "Mariakani"]},
      {"name": "Kwale", "cities": ["Kwale", "Ukunda", "Diani Beach", "Msambweni"]}
    ],
    "MY": [
      {"name": "Selangor", "cities": ["Shah Alam", "Petaling Jaya", "Subang Jaya", "Klang", "Kajang", "Ampang", "Puchong", "Serdang", "Rawang", "Sepang", "Cyberjaya"]},
      {"name": "Kuala Lumpur", "cities": ["Kuala Lumpur", "Bangsar", "Bukit Bintang", "Cheras", "Setapak", "Kepong", "Wangsa Maju"]},
      {"name": "Penang", "cities": ["George Town", "Butterworth", "Bukit Mertajam", "Nibong Tebal", "Bayan Lepas", "Balik Pulau"]},
      {"name": "Johor", "cities": ["Johor Bahru", "Pasir Gudang", "Skudai", "Batu Pahat", "Muar", "Kluang", "Pontian", "Kulai", "Segamat", "Kota Tinggi"]},
      {"name": "Perak", "cities": ["Ipoh", "Taiping", "Sitiawan", "Teluk Intan", "Lumut", "Manjung", "Kampar", "Batu Gajah"]},
      {"name": "Kedah", "cities": ["Alor Setar", "Sungai Petani", "Kulim", "Langkawi", "Jitra", "Baling"]},
      {"name": "Sarawak", "cities": ["Kuching", "Miri", "Sibu", "Bintulu", "Limbang", "Mukah", "Sarikei"]},
      {"name": "Sabah", "cities": ["Kota Kinabalu", "Sandakan", "Tawau", "Lahad Datu", "Keningau", "Semporna"]},
      {"name": "Pahang", "cities": ["Kuantan", "Temerloh", "Bentong", "Pekan", "Cameron Highlands", "Genting Highlands"]},
      {"name": "Negeri Sembilan", "cities": ["Seremban", "Port Dickson", "Nilai", "Bahau", "Rembau"]},
      {"name": "Melaka", "cities": ["Melaka City", "Ayer Keroh", "Alor Gajah", "Jasin"]},
      {"name": "Terengganu", "cities": ["Kuala Terengganu", "Kemaman", "Dungun", "Marang", "Setiu"]},
      {"name": "Kelantan", "cities": ["Kota Bharu", "Pasir Mas", "Tanah Merah", "Bachok", "Kuala Krai"]}
    ],
    "MV": [
      {"name": "Malé", "cities": ["Malé", "Hulhumalé", "Villimalé"]},
      {"name": "Addu City", "cities": ["Hithadhoo", "Feydhoo", "Maradhoo", "Hulhumeedhoo"]},
      {"name": "Fuvahmulah", "cities": ["Fuvahmulah"]},
      {"name": "North Malé Atoll", "cities": ["Thulusdhoo", "Huraa", "Himmafushi", "Gulhi"]},
      {"name": "South Malé Atoll", "cities": ["Maafushi", "Guraidhoo"]},
      {"name": "Ari Atoll", "cities": ["Mahibadhoo", "Maamigili", "Omadhoo"]},
      {"name": "Baa Atoll", "cities": ["Eydhafushi", "Thulhaadhoo", "Dharavandhoo"]},
      {"name": "Laamu Atoll", "cities": ["Fonadhoo", "Hithadhoo", "Gan"]}
    ],
    "MX": [
      {"name": "Mexico City", "cities": ["Mexico City", "Coyoacán", "Gustavo A. Madero", "Iztapalapa", "Álvaro Obregón", "Tlalpan", "Xochimilco", "Cuauhtémoc", "Miguel Hidalgo", "Benito Juárez"]},
      {"name": "Jalisco", "cities": ["Guadalajara", "Zapopan", "Tlaquepaque", "Tonalá", "Puerto Vallarta", "Lagos de Moreno", "Tlajomulco", "El Salto", "Tepatitlán"]},
      {"name": "Nuevo León", "cities": ["Monterrey", "Guadalupe", "San Nicolás de los Garza", "Apodaca", "Santa Catarina", "General Escobedo", "San Pedro Garza García", "Juárez"]},
      {"name": "State of Mexico", "cities": ["Toluca", "Ecatepec", "Nezahualcóyotl", "Naucalpan", "Tlalnepantla", "Chimalhuacán", "Cuautitlán Izcalli", "Atizapán", "Texcoco", "Metepec"]},
      {"name": "Veracruz", "cities": ["Veracruz", "Xalapa", "Coatzacoalcos", "Córdoba", "Poza Rica", "Orizaba", "Minatitlán", "Boca del Río"]},
      {"name": "Puebla", "cities": ["Puebla", "Tehuacán", "Atlixco", "San Martín Texmelucan", "Cholula", "Amozoc", "Huauchinango"]},
      {"name": "Guanajuato", "cities": ["León", "Irapuato", "Celaya", "Salamanca", "Guanajuato", "San Miguel de Allende", "Silao", "Dolores Hidalgo"]},
      {"name": "Chihuahua", "cities": ["Juárez", "Chihuahua", "Cuauhtémoc", "Delicias", "Parral", "Nuevo Casas Grandes"]},
      {"name": "Baja California", "cities": ["Tijuana", "Mexicali", "Ensenada", "Rosarito", "Tecate"]},
      {"name": "Sonora", "cities": ["Hermosillo", "Ciudad Obregón", "Nogales", "San Luis Río Colorado", "Guaymas", "Navojoa"]},
      {"name": "Yucatán", "cities": ["Mérida", "Valladolid", "Tizimín", "Progreso", "Kanasín", "Umán"]},
      {"name": "Quintana Roo", "cities": ["Cancún", "Playa del Carmen", "Chetumal", "Cozumel", "Tulum", "Isla Mujeres"]}
    ],
    "MM": [
      {"name": "Yangon", "cities": ["Yangon", "Thanlyin", "Insein", "Mingaladon", "Hlaing", "Kamaryut"]},
      {"name": "Mandalay", "cities": ["Mandalay", "Amarapura", "Sagaing", "Mogok", "Meiktila", "Myingyan", "Pyin Oo Lwin"]},
      {"name": "Naypyidaw", "cities": ["Naypyidaw", "Pyinmana", "Tatkon", "Lewe"]},
      {"name": "Shan State", "cities": ["Taunggyi", "Lashio", "Kengtung", "Hsipaw", "Kalaw", "Nyaungshwe"]},
      {"name": "Kachin State", "cities": ["Myitkyina", "Bhamo", "Mohnyin", "Mogaung"]},
      {"name": "Mon State", "cities": ["Mawlamyine", "Thaton", "Mudon", "Ye"]},
      {"name": "Rakhine State", "cities": ["Sittwe", "Thandwe", "Kyaukpyu", "Mrauk U"]},
      {"name": "Bago Region", "cities": ["Bago", "Pyay", "Taungoo", "Thayarwady"]},
      {"name": "Ayeyarwady Region", "cities": ["Pathein", "Maubin", "Myaungmya", "Labutta"]}
    ],
    "NP": [
      {"name": "Bagmati Province", "cities": ["Kathmandu", "Lalitpur", "Bhaktapur", "Kirtipur", "Madhyapur Thimi", "Dhulikhel", "Hetauda", "Bharatpur"]},
      {"name": "Province No. 1", "cities": ["Biratnagar", "Dharan", "Itahari", "Damak", "Mechinagar", "Inaruwa", "Birtamod"]},
      {"name": "Province No. 2", "cities": ["Janakpur", "Birgunj", "Rajbiraj", "Gaur", "Kalaiya", "Lahan", "Jaleshwar"]},
      {"name": "Gandaki Province", "cities": ["Pokhara", "Baglung", "Gorkha", "Damauli", "Besisahar", "Beni", "Waling"]},
      {"name": "Lumbini Province", "cities": ["Butwal", "Bhairahawa", "Nepalgunj", "Tulsipur", "Tansen", "Kapilvastu", "Dang"]},
      {"name": "Karnali Province", "cities": ["Birendranagar", "Jumla", "Dailekh", "Dunai", "Gamgadhi"]},
      {"name": "Sudurpashchim Province", "cities": ["Dhangadhi", "Mahendranagar", "Dipayal", "Dadeldhura", "Tikapur", "Attariya"]}
    ],
    "NZ": [
      {"name": "Auckland", "cities": ["Auckland", "North Shore", "Manukau", "Waitakere", "Papakura", "Albany", "Takapuna", "Henderson"]},
      {"name": "Wellington", "cities": ["Wellington", "Lower Hutt", "Upper Hutt", "Porirua", "Paraparaumu", "Petone", "Masterton"]},
      {"name": "Canterbury", "cities": ["Christchurch", "Timaru", "Ashburton", "Rolleston", "Rangiora", "Kaiapoi"]},
      {"name": "Waikato", "cities": ["Hamilton", "Cambridge", "Te Awamutu", "Tokoroa", "Matamata", "Morrinsville"]},
      {"name": "Bay of Plenty", "cities": ["Tauranga", "Rotorua", "Whakatane", "Taupo", "Mount Maunganui", "Te Puke"]},
      {"name": "Otago", "cities": ["Dunedin", "Queenstown", "Oamaru", "Alexandra", "Wanaka", "Cromwell"]},
      {"name": "Manawatu-Wanganui", "cities": ["Palmerston North", "Whanganui", "Levin", "Feilding", "Marton"]},
      {"name": "Hawke's Bay", "cities": ["Napier", "Hastings", "Havelock North", "Waipukurau"]},
      {"name": "Northland", "cities": ["Whangarei", "Kerikeri", "Kaikohe", "Kaitaia", "Dargaville"]},
      {"name": "Taranaki", "cities": ["New Plymouth", "Hawera", "Stratford", "Inglewood"]},
      {"name": "Southland", "cities": ["Invercargill", "Gore", "Te Anau", "Winton"]}
    ],
    "NG": [
      {"name": "Lagos", "cities": ["Lagos", "Ikeja", "Victoria Island", "Lekki", "Surulere", "Yaba", "Ikorodu", "Oshodi", "Agege", "Apapa", "Mushin"]},
      {"name": "Kano", "cities": ["Kano", "Wudil", "Gwarzo", "Bichi", "Rano", "Dala"]},
      {"name": "Rivers", "cities": ["Port Harcourt", "Obio-Akpor", "Bonny", "Okrika", "Eleme"]},
      {"name": "Oyo", "cities": ["Ibadan", "Ogbomosho", "Oyo", "Iseyin", "Saki", "Eruwa"]},
      {"name": "Kaduna", "cities": ["Kaduna", "Zaria", "Kafanchan", "Kagoro", "Saminaka"]},
      {"name": "Abuja FCT", "cities": ["Abuja", "Gwagwalada", "Kubwa", "Kuje", "Bwari"]},
      {"name": "Anambra", "cities": ["Onitsha", "Nnewi", "Awka", "Ekwulobia", "Ogidi"]},
      {"name": "Delta", "cities": ["Asaba", "Warri", "Sapele", "Ughelli", "Agbor", "Effurun"]},
      {"name": "Enugu", "cities": ["Enugu", "Nsukka", "Agbani", "Oji River", "Awgu"]},
      {"name": "Imo", "cities": ["Owerri", "Orlu", "Okigwe", "Mbaise", "Oguta"]},
      {"name": "Osun", "cities": ["Osogbo", "Ile-Ife", "Ilesa", "Ede", "Iwo", "Ikire"]},
      {"name": "Ogun", "cities": ["Abeokuta", "Ijebu Ode", "Sagamu", "Ota", "Ifo", "Ilaro"]}
    ],
    "OM": [
      {"name": "Muscat", "cities": ["Muscat", "Seeb", "Mutrah", "Bawshar", "Quriyat", "Al Amerat"]},
      {"name": "Dhofar", "cities": ["Salalah", "Thamrit", "Rakhyut", "Mirbat", "Taqah"]},
      {"name": "North Al Batinah", "cities": ["Sohar", "Saham", "Shinas", "Liwa", "Al Khabourah"]},
      {"name": "South Al Batinah", "cities": ["Rustaq", "Nakhal", "Barka", "Al Musannah", "Wadi Al Ma'awil"]},
      {"name": "Al Dakhiliyah", "cities": ["Nizwa", "Bahla", "Adam", "Manah", "Izki"]},
      {"name": "North Ash Sharqiyah", "cities": ["Ibra", "Mudaybi", "Bidiyah", "Qabil"]},
      {"name": "South Ash Sharqiyah", "cities": ["Sur", "Ibra", "Jalan Bani Bu Ali", "Masirah"]}
    ],
    "PK": [
      {"name": "Punjab", "cities": ["Lahore", "Faisalabad", "Rawalpindi", "Multan", "Gujranwala", "Sialkot", "Sargodha", "Bahawalpur", "Gujrat", "Sahiwal", "Sheikhupura", "Rahim Yar Khan", "Jhang", "Kasur", "Okara", "Mianwali", "Chiniot", "Jhelum", "Khanewal"]},
      {"name": "Sindh", "cities": ["Karachi", "Hyderabad", "Sukkur", "Larkana", "Nawabshah", "Mirpur Khas", "Jacobabad", "Shikarpur", "Khairpur", "Thatta", "Dadu", "Sanghar"]},
      {"name": "Khyber Pakhtunkhwa", "cities": ["Peshawar", "Mardan", "Abbottabad", "Swat", "Kohat", "Dera Ismail Khan", "Bannu", "Charsadda", "Nowshera", "Haripur", "Mansehra"]},
      {"name": "Balochistan", "cities": ["Quetta", "Gwadar", "Turbat", "Khuzdar", "Hub", "Chaman", "Sibi", "Zhob", "Loralai"]},
      {"name": "Islamabad Capital Territory", "cities": ["Islamabad", "Bhara Kahu", "Golra", "Sihala", "Tarnol"]},
      {"name": "Azad Kashmir", "cities": ["Muzaffarabad", "Mirpur", "Rawalakot", "Kotli", "Bhimber", "Bagh"]},
      {"name": "Gilgit-Baltistan", "cities": ["Gilgit", "Skardu", "Chilas", "Hunza", "Ghanche", "Astore"]}
    ],
    "PH": [
      {"name": "Metro Manila", "cities": ["Manila", "Quezon City", "Makati", "Pasig", "Taguig", "Parañaque", "Caloocan", "Pasay", "Marikina", "Muntinlupa", "Las Piñas", "Mandaluyong", "Valenzuela"]},
      {"name": "Cebu", "cities": ["Cebu City", "Mandaue", "Lapu-Lapu", "Talisay", "Danao", "Carcar", "Toledo", "Bogo"]},
      {"name": "Cavite", "cities": ["Bacoor", "Imus", "Dasmariñas", "General Trias", "Cavite City", "Tagaytay", "Trece Martires", "Silang"]},
      {"name": "Laguna", "cities": ["San Pedro", "Biñan", "Santa Rosa", "Calamba", "San Pablo", "Los Baños", "Cabuyao"]},
      {"name": "Rizal", "cities": ["Antipolo", "Cainta", "Taytay", "Binangonan", "Rodriguez", "San Mateo", "Angono"]},
      {"name": "Bulacan", "cities": ["Malolos", "Meycauayan", "San Jose del Monte", "Marilao", "Bocaue", "Plaridel", "Baliwag"]},
      {"name": "Pampanga", "cities": ["Angeles City", "San Fernando", "Mabalacat", "Mexico", "Porac", "Apalit", "Lubao"]},
      {"name": "Davao del Sur", "cities": ["Davao City", "Digos", "Sta. Cruz", "Toril", "Bunawan"]},
      {"name": "Batangas", "cities": ["Batangas City", "Lipa", "Tanauan", "Santo Tomas", "Nasugbu", "Balayan"]},
      {"name": "Iloilo", "cities": ["Iloilo City", "Passi", "Oton", "Santa Barbara", "San Miguel"]},
      {"name": "Zamboanga del Sur", "cities": ["Zamboanga City", "Pagadian", "Ipil", "Molave"]},
      {"name": "Negros Occidental", "cities": ["Bacolod", "San Carlos", "Silay", "Talisay", "Kabankalan", "Cadiz"]}
    ],
    "QA": [
      {"name": "Doha", "cities": ["Doha", "West Bay", "The Pearl", "Al Sadd", "Al Wakrah", "Msheireb", "Lusail"]},
      {"name": "Al Rayyan", "cities": ["Al Rayyan", "Education City", "Al Sheehaniya", "Dukhan"]},
      {"name": "Al Wakrah", "cities": ["Al Wakrah", "Al Wukair", "Mesaieed"]},
      {"name": "Al Khor", "cities": ["Al Khor", "Al Thakhira", "Ras Laffan"]},
      {"name": "Umm Salal", "cities": ["Umm Salal Mohammed", "Umm Salal Ali"]},
      {"name": "Al Daayen", "cities": ["Lusail", "Umm Qarn", "Simaisma"]},
      {"name": "Al Shamal", "cities": ["Madinat ash Shamal", "Al Ruwais", "Al Ghuwariyah"]}
    ],
    "RU": [
      {"name": "Moscow", "cities": ["Moscow", "Zelenograd", "Troitsk", "Shcherbinka", "Kommunarka"]},
      {"name": "Saint Petersburg", "cities": ["Saint Petersburg", "Kronstadt", "Pushkin", "Peterhof", "Kolpino", "Lomonosov"]},
      {"name": "Moscow Oblast", "cities": ["Balashikha", "Khimki", "Podolsk", "Mytishchi", "Korolev", "Lyubertsy", "Krasnogorsk", "Odintsovo", "Dolgoprudny", "Domodedovo", "Zhukovsky", "Shchyolkovo", "Sergiev Posad"]},
      {"name": "Krasnodar Krai", "cities": ["Krasnodar", "Sochi", "Novorossiysk", "Armavir", "Anapa", "Gelendzhik", "Yeysk", "Tuapse"]},
      {"name": "Tatarstan", "cities": ["Kazan", "Naberezhnye Chelny", "Nizhnekamsk", "Almetyevsk", "Zelenodolsk", "Bugulma", "Elabuga"]},
      {"name": "Sverdlovsk Oblast", "cities": ["Yekaterinburg", "Nizhny Tagil", "Kamensk-Uralsky", "Pervouralsk", "Serov", "Novouralsk", "Verkhnyaya Pyshma"]},
      {"name": "Novosibirsk Oblast", "cities": ["Novosibirsk", "Berdsk", "Iskitim", "Ob", "Akademgorodok", "Karasuk"]},
      {"name": "Samara Oblast", "cities": ["Samara", "Togliatti", "Syzran", "Novokuybyshevsk", "Chapaevsk", "Zhigulevsk"]},
      {"name": "Nizhny Novgorod Oblast", "cities": ["Nizhny Novgorod", "Dzerzhinsk", "Arzamas", "Sarov", "Bor", "Kstovo"]},
      {"name": "Chelyabinsk Oblast", "cities": ["Chelyabinsk", "Magnitogorsk", "Zlatoust", "Miass", "Kopeysk", "Ozyorsk"]},
      {"name": "Rostov Oblast", "cities": ["Rostov-on-Don", "Taganrog", "Shakhty", "Novocherkassk", "Bataysk", "Volgodonsk", "Novoshakhtinsk"]},
      {"name": "Bashkortostan", "cities": ["Ufa", "Sterlitamak", "Salavat", "Neftekamsk", "Oktyabrsky", "Tuymazy"]}
    ],
    "SA": [
      {"name": "Riyadh", "cities": ["Riyadh", "Diriyah", "Al Kharj", "Majmaah", "Wadi ad-Dawasir", "Shaqra"]},
      {"name": "Makkah", "cities": ["Jeddah", "Mecca", "Taif", "Rabigh", "Al Qunfudhah", "Al Lith"]},
      {"name": "Eastern Province", "cities": ["Dammam", "Al Khobar", "Dhahran", "Jubail", "Al Ahsa", "Qatif", "Hafar Al-Batin", "Khafji"]},
      {"name": "Medina", "cities": ["Medina", "Yanbu", "Al Ula", "Badr", "Khaybar"]},
      {"name": "Asir", "cities": ["Abha", "Khamis Mushait", "Bisha", "Muhayil", "Dhahran Al Janub"]},
      {"name": "Jazan", "cities": ["Jazan", "Sabya", "Abu Arish", "Samtah", "Ahad Al Masarihah"]},
      {"name": "Qassim", "cities": ["Buraydah", "Unaizah", "Al Rass", "Al Bukayriyah", "Al Badayea"]},
      {"name": "Tabuk", "cities": ["Tabuk", "Duba", "Tayma", "Umluj", "Al Wajh"]},
      {"name": "Hail", "cities": ["Hail", "Baqaa", "Mawqaq", "Al Shamli"]},
      {"name": "Najran", "cities": ["Najran", "Sharurah", "Habuna"]},
      {"name": "Al Bahah", "cities": ["Al Bahah", "Baljurashi", "Al Makhwah"]},
      {"name": "Northern Borders", "cities": ["Arar", "Rafha", "Turaif"]}
    ],
    "SG": [
      {"name": "Central Region", "cities": ["Downtown Core", "Orchard", "Marina Bay", "Chinatown", "Little India", "Tanjong Pagar", "Novena", "Bishan", "Bukit Merah", "Queenstown", "Kallang"]},
      {"name": "North Region", "cities": ["Woodlands", "Yishun", "Sembawang", "Mandai", "Admiralty"]},
      {"name": "North-East Region", "cities": ["Sengkang", "Punggol", "Hougang", "Serangoon", "Ang Mo Kio"]},
      {"name": "East Region", "cities": ["Tampines", "Bedok", "Pasir Ris", "Changi", "Paya Lebar"]},
      {"name": "West Region", "cities": ["Jurong East", "Jurong West", "Clementi", "Bukit Batok", "Choa Chu Kang", "Boon Lay", "Pioneer", "Tengah"]}
    ],
    "ZA": [
      {"name": "Gauteng", "cities": ["Johannesburg", "Pretoria", "Soweto", "Sandton", "Midrand", "Centurion", "Roodepoort", "Randburg", "Boksburg", "Kempton Park", "Alberton", "Germiston", "Benoni", "Springs"]},
      {"name": "Western Cape", "cities": ["Cape Town", "Stellenbosch", "Paarl", "George", "Worcester", "Bellville", "Somerset West", "Hermanus", "Knysna", "Mossel Bay"]},
      {"name": "KwaZulu-Natal", "cities": ["Durban", "Pietermaritzburg", "Richards Bay", "Newcastle", "Port Shepstone", "Ladysmith", "Pinetown", "Umhlanga", "Ballito"]},
      {"name": "Eastern Cape", "cities": ["Port Elizabeth", "East London", "Mthatha", "Queenstown", "Grahamstown", "King William's Town", "Cradock", "Uitenhage"]},
      {"name": "Free State", "cities": ["Bloemfontein", "Welkom", "Bethlehem", "Kroonstad", "Sasolburg", "Parys", "Virginia"]},
      {"name": "Mpumalanga", "cities": ["Nelspruit", "Witbank", "Secunda", "Middelburg", "Barberton", "White River", "Ermelo"]},
      {"name": "Limpopo", "cities": ["Polokwane", "Tzaneen", "Mokopane", "Thohoyandou", "Louis Trichardt", "Musina", "Phalaborwa"]},
      {"name": "North West", "cities": ["Rustenburg", "Potchefstroom", "Klerksdorp", "Mahikeng", "Brits", "Hartbeespoort"]},
      {"name": "Northern Cape", "cities": ["Kimberley", "Upington", "Springbok", "De Aar", "Kuruman"]}
    ],
    "KR": [
      {"name": "Seoul", "cities": ["Seoul", "Gangnam", "Jongno", "Mapo", "Yongsan", "Songpa", "Seocho", "Nowon", "Gangbuk", "Yeongdeungpo"]},
      {"name": "Busan", "cities": ["Busan", "Haeundae", "Jung-gu", "Busanjin", "Saha", "Dongnae", "Yeonje"]},
      {"name": "Incheon", "cities": ["Incheon", "Namdong", "Bupyeong", "Seo-gu", "Yeonsu", "Jung-gu"]},
      {"name": "Daegu", "cities": ["Daegu", "Suseong", "Dalseo", "Buk-gu", "Nam-gu", "Dong-gu"]},
      {"name": "Daejeon", "cities": ["Daejeon", "Yuseong", "Seo-gu", "Daedeok", "Jung-gu"]},
      {"name": "Gwangju", "cities": ["Gwangju", "Seo-gu", "Nam-gu", "Buk-gu", "Gwangsan"]},
      {"name": "Ulsan", "cities": ["Ulsan", "Nam-gu", "Dong-gu", "Buk-gu", "Ulju"]},
      {"name": "Gyeonggi", "cities": ["Suwon", "Seongnam", "Goyang", "Yongin", "Bucheon", "Ansan", "Anyang", "Namyangju", "Hwaseong", "Uijeongbu", "Siheung", "Pyeongtaek", "Gimpo", "Gwangmyeong"]},
      {"name": "Gangwon", "cities": ["Chuncheon", "Wonju", "Gangneung", "Sokcho", "Donghae", "Samcheok"]},
      {"name": "North Chungcheong", "cities": ["Cheongju", "Chungju", "Jecheon", "Eumseong", "Jincheon"]},
      {"name": "South Chungcheong", "cities": ["Cheonan", "Asan", "Seosan", "Dangjin", "Gongju", "Boryeong"]},
      {"name": "North Jeolla", "cities": ["Jeonju", "Iksan", "Gunsan", "Jeongeup", "Namwon", "Gimje"]},
      {"name": "South Jeolla", "cities": ["Mokpo", "Yeosu", "Suncheon", "Naju", "Gwangyang", "Muan"]},
      {"name": "North Gyeongsang", "cities": ["Pohang", "Gumi", "Gyeongju", "Andong", "Gimcheon", "Yeongju", "Sangju"]},
      {"name": "South Gyeongsang", "cities": ["Changwon", "Gimhae", "Jinju", "Yangsan", "Geoje", "Tongyeong", "Sacheon"]},
      {"name": "Jeju", "cities": ["Jeju City", "Seogwipo"]}
    ],
    "ES": [
      {"name": "Madrid", "cities": ["Madrid", "Móstoles", "Alcalá de Henares", "Fuenlabrada", "Leganés", "Getafe", "Alcorcón", "Torrejón de Ardoz", "Parla", "Alcobendas", "Las Rozas"]},
      {"name": "Catalonia", "cities": ["Barcelona", "L'Hospitalet de Llobregat", "Badalona", "Terrassa", "Sabadell", "Mataró", "Santa Coloma de Gramenet", "Cornellà de Llobregat", "Girona", "Tarragona", "Lleida", "Reus"]},
      {"name": "Andalusia", "cities": ["Seville", "Málaga", "Córdoba", "Granada", "Jerez de la Frontera", "Almería", "Huelva", "Cádiz", "Jaén", "Marbella", "Dos Hermanas"]},
      {"name": "Valencia", "cities": ["Valencia", "Alicante", "Elche", "Castellón de la Plana", "Torrevieja", "Orihuela", "Benidorm", "Gandía", "Paterna"]},
      {"name": "Basque Country", "cities": ["Bilbao", "Vitoria-Gasteiz", "San Sebastián", "Barakaldo", "Getxo", "Irun", "Portugalete"]},
      {"name": "Galicia", "cities": ["Vigo", "A Coruña", "Ourense", "Lugo", "Santiago de Compostela", "Pontevedra", "Ferrol"]},
      {"name": "Castile and León", "cities": ["Valladolid", "Burgos", "Salamanca", "León", "Palencia", "Segovia", "Zamora", "Ávila"]},
      {"name": "Canary Islands", "cities": ["Las Palmas de Gran Canaria", "Santa Cruz de Tenerife", "La Laguna", "Telde", "Arona", "Arrecife"]},
      {"name": "Aragon", "cities": ["Zaragoza", "Huesca", "Teruel", "Calatayud"]},
      {"name": "Balearic Islands", "cities": ["Palma de Mallorca", "Ibiza", "Manacor", "Mahón", "Inca"]}
    ],
    "LK": [
      {"name": "Western Province", "cities": ["Colombo", "Sri Jayawardenepura Kotte", "Dehiwala-Mount Lavinia", "Moratuwa", "Negombo", "Kelaniya", "Kotte", "Kolonnawa", "Maharagama", "Kaduwela"]},
      {"name": "Central Province", "cities": ["Kandy", "Matale", "Nuwara Eliya", "Gampola", "Nawalapitiya", "Hatton", "Dambulla"]},
      {"name": "Southern Province", "cities": ["Galle", "Matara", "Hambantota", "Ambalangoda", "Weligama", "Tangalle", "Unawatuna"]},
      {"name": "Northern Province", "cities": ["Jaffna", "Kilinochchi", "Vavuniya", "Mannar", "Mullaitivu", "Point Pedro"]},
      {"name": "Eastern Province", "cities": ["Batticaloa", "Trincomalee", "Ampara", "Kalmunai", "Akkaraipattu"]},
      {"name": "North Western Province", "cities": ["Kurunegala", "Puttalam", "Chilaw", "Kuliyapitiya", "Pannala"]},
      {"name": "North Central Province", "cities": ["Anuradhapura", "Polonnaruwa", "Mihintale", "Medawachchiya"]},
      {"name": "Uva Province", "cities": ["Badulla", "Bandarawela", "Monaragala", "Ella", "Wellawaya"]},
      {"name": "Sabaragamuwa Province", "cities": ["Ratnapura", "Kegalle", "Balangoda", "Embilipitiya", "Mawanella"]}
    ],
    "TH": [
      {"name": "Bangkok", "cities": ["Bangkok", "Thonburi", "Khlong Toei", "Chatuchak", "Phaya Thai", "Bang Kapi", "Lat Phrao", "Min Buri", "Phra Nakhon", "Sathon"]},
      {"name": "Chiang Mai", "cities": ["Chiang Mai", "San Kamphaeng", "Hang Dong", "Mae Rim", "San Sai", "Doi Saket"]},
      {"name": "Phuket", "cities": ["Phuket Town", "Patong", "Karon", "Kata", "Rawai", "Kamala", "Chalong"]},
      {"name": "Chonburi", "cities": ["Pattaya", "Chonburi", "Sri Racha", "Laem Chabang", "Bang Lamung", "Sattahip"]},
      {"name": "Nonthaburi", "cities": ["Nonthaburi", "Pak Kret", "Bang Yai", "Bang Bua Thong", "Sai Noi"]},
      {"name": "Samut Prakan", "cities": ["Samut Prakan", "Pak Nam", "Bang Phli", "Phra Pradaeng", "Bang Bo"]},
      {"name": "Pathum Thani", "cities": ["Rangsit", "Pathum Thani", "Thanyaburi", "Khlong Luang", "Lam Luk Ka"]},
      {"name": "Nakhon Ratchasima", "cities": ["Nakhon Ratchasima", "Pak Chong", "Bua Yai", "Phimai", "Dan Khun Thot"]},
      {"name": "Khon Kaen", "cities": ["Khon Kaen", "Ban Phai", "Chum Phae", "Phu Wiang", "Kranuan"]},
      {"name": "Songkhla", "cities": ["Hat Yai", "Songkhla", "Sadao", "Na Thawi", "Ranot"]},
      {"name": "Surat Thani", "cities": ["Surat Thani", "Ko Samui", "Phunphin", "Chaiya", "Kanchanadit"]},
      {"name": "Udon Thani", "cities": ["Udon Thani", "Nong Han", "Ban Dung", "Kumphawapi", "Phen"]},
      {"name": "Chiang Rai", "cities": ["Chiang Rai", "Mae Sai", "Chiang Saen", "Mae Chan", "Wiang Pa Pao"]}
    ],
    "TR": [
      {"name": "Istanbul", "cities": ["Istanbul", "Kadıköy", "Üsküdar", "Beşiktaş", "Fatih", "Bakırköy", "Beyoğlu", "Şişli", "Sarıyer", "Maltepe", "Pendik", "Kartal", "Ümraniye", "Bahçelievler"]},
      {"name": "Ankara", "cities": ["Ankara", "Çankaya", "Keçiören", "Mamak", "Etimesgut", "Yenimahalle", "Sincan", "Altındağ", "Polatlı"]},
      {"name": "Izmir", "cities": ["Izmir", "Bornova", "Karşıyaka", "Konak", "Buca", "Çiğli", "Bayraklı", "Gaziemir", "Urla", "Çeşme"]},
      {"name": "Bursa", "cities": ["Bursa", "Nilüfer", "Osmangazi", "Yıldırım", "Gemlik", "Mudanya", "İnegöl", "Kestel"]},
      {"name": "Antalya", "cities": ["Antalya", "Alanya", "Manavgat", "Serik", "Kemer", "Kumluca", "Muratpaşa", "Kepez"]},
      {"name": "Adana", "cities": ["Adana", "Seyhan", "Yüreğir", "Çukurova", "Sarıçam", "Ceyhan", "Kozan"]},
      {"name": "Konya", "cities": ["Konya", "Selçuklu", "Meram", "Karatay", "Ereğli", "Akşehir", "Seydişehir"]},
      {"name": "Gaziantep", "cities": ["Gaziantep", "Şahinbey", "Şehitkamil", "Nizip", "Nurdağı", "İslahiye"]},
      {"name": "Mersin", "cities": ["Mersin", "Tarsus", "Yenişehir", "Mezitli", "Akdeniz", "Toroslar", "Silifke"]},
      {"name": "Kocaeli", "cities": ["İzmit", "Gebze", "Darıca", "Çayırova", "Körfez", "Gölcük", "Kartepe"]},
      {"name": "Diyarbakır", "cities": ["Diyarbakır", "Bağlar", "Kayapınar", "Sur", "Yenişehir", "Ergani"]},
      {"name": "Muğla", "cities": ["Muğla", "Bodrum", "Fethiye", "Marmaris", "Datça", "Dalaman", "Köyceğiz"]}
    ],
    "AE": [
      {"name": "Dubai", "cities": ["Dubai", "Deira", "Bur Dubai", "Jumeirah", "Marina", "Downtown Dubai", "Al Barsha", "Palm Jumeirah", "JBR", "Business Bay", "DIFC", "Al Quoz"]},
      {"name": "Abu Dhabi", "cities": ["Abu Dhabi", "Al Ain", "Mussafah", "Khalifa City", "Al Reem Island", "Yas Island", "Saadiyat Island", "Al Shamkha", "Mohammed Bin Zayed City"]},
      {"name": "Sharjah", "cities": ["Sharjah", "Khor Fakkan", "Kalba", "Al Dhaid", "Dibba Al-Hisn", "Al Hamriyah"]},
      {"name": "Ajman", "cities": ["Ajman", "Al Nuaimiya", "Al Rashidiya", "Al Jurf", "Masfout"]},
      {"name": "Ras Al Khaimah", "cities": ["Ras Al Khaimah", "Al Hamra", "Al Nakheel", "Al Jazirah", "Khuzam"]},
      {"name": "Fujairah", "cities": ["Fujairah", "Dibba", "Al Bidya", "Masafi"]},
      {"name": "Umm Al Quwain", "cities": ["Umm Al Quwain", "Falaj Al Mualla", "Al Salamah"]}
    ],
    "GB": [
      {"name": "England", "cities": ["London", "Birmingham", "Manchester", "Leeds", "Liverpool", "Sheffield", "Bristol", "Newcastle", "Nottingham", "Leicester", "Southampton", "Brighton", "Plymouth", "Reading", "Derby", "Wolverhampton", "Cambridge", "Oxford", "Portsmouth", "York"]},
      {"name": "Scotland", "cities": ["Edinburgh", "Glasgow", "Aberdeen", "Dundee", "Inverness", "Perth", "Stirling", "Dunfermline", "Livingston", "Paisley"]},
      {"name": "Wales", "cities": ["Cardiff", "Swansea", "Newport", "Wrexham", "Barry", "Neath", "Bridgend", "Cwmbran", "Llanelli"]},
      {"name": "Northern Ireland", "cities": ["Belfast", "Derry", "Lisburn", "Newtownabbey", "Bangor", "Craigavon", "Newry", "Carrickfergus"]},
      {"name": "Greater London", "cities": ["Westminster", "Camden", "Kensington", "Greenwich", "Hackney", "Islington", "Southwark", "Tower Hamlets", "Lambeth", "Wandsworth", "Hammersmith", "Brent", "Barnet", "Ealing", "Croydon"]},
      {"name": "West Midlands", "cities": ["Birmingham", "Coventry", "Wolverhampton", "Dudley", "Walsall", "Solihull", "West Bromwich"]},
      {"name": "Greater Manchester", "cities": ["Manchester", "Salford", "Bolton", "Stockport", "Oldham", "Rochdale", "Bury", "Wigan", "Tameside"]},
      {"name": "West Yorkshire", "cities": ["Leeds", "Bradford", "Wakefield", "Huddersfield", "Halifax", "Dewsbury", "Batley"]},
      {"name": "South Yorkshire", "cities": ["Sheffield", "Doncaster", "Rotherham", "Barnsley"]},
      {"name": "Merseyside", "cities": ["Liverpool", "Wirral", "St Helens", "Knowsley", "Sefton", "Bootle"]}
    ],
    "US": [
      {"name": "California", "cities": ["Los Angeles", "San Diego", "San Jose", "San Francisco", "Fresno", "Sacramento", "Long Beach", "Oakland", "Bakersfield", "Anaheim", "Santa Ana", "Riverside", "Stockton", "Irvine", "Chula Vista", "Fremont", "San Bernardino", "Modesto", "Fontana", "Santa Clarita", "Moreno Valley", "Glendale", "Huntington Beach"]},
      {"name": "Texas", "cities": ["Houston", "San Antonio", "Dallas", "Austin", "Fort Worth", "El Paso", "Arlington", "Corpus Christi", "Plano", "Lubbock", "Laredo", "Irving", "Garland", "Amarillo", "Grand Prairie", "McKinney", "Frisco", "Brownsville", "Pasadena", "Killeen"]},
      {"name": "Florida", "cities": ["Jacksonville", "Miami", "Tampa", "Orlando", "St. Petersburg", "Hialeah", "Tallahassee", "Fort Lauderdale", "Port St. Lucie", "Cape Coral", "Pembroke Pines", "Hollywood", "Gainesville", "Miramar", "Coral Springs", "Clearwater", "Palm Bay", "Pompano Beach", "West Palm Beach"]},
      {"name": "New York", "cities": ["New York City", "Buffalo", "Rochester", "Yonkers", "Syracuse", "Albany", "New Rochelle", "Mount Vernon", "Schenectady", "Utica", "White Plains", "Troy", "Niagara Falls", "Binghamton", "Ithaca"]},
      {"name": "Illinois", "cities": ["Chicago", "Aurora", "Naperville", "Joliet", "Rockford", "Springfield", "Elgin", "Peoria", "Champaign", "Waukegan", "Cicero", "Bloomington", "Arlington Heights", "Evanston", "Schaumburg", "Decatur"]},
      {"name": "Pennsylvania", "cities": ["Philadelphia", "Pittsburgh", "Allentown", "Reading", "Scranton", "Bethlehem", "Lancaster", "Harrisburg", "Erie", "York", "Wilkes-Barre", "Chester", "Easton"]},
      {"name": "Ohio", "cities": ["Columbus", "Cleveland", "Cincinnati", "Toledo", "Akron", "Dayton", "Parma", "Canton", "Youngstown", "Lorain", "Hamilton", "Springfield", "Kettering", "Lakewood"]},
      {"name": "Georgia", "cities": ["Atlanta", "Augusta", "Columbus", "Macon", "Savannah", "Athens", "Sandy Springs", "Roswell", "Johns Creek", "Albany", "Warner Robins", "Alpharetta", "Marietta", "Smyrna"]},
      {"name": "North Carolina", "cities": ["Charlotte", "Raleigh", "Greensboro", "Durham", "Winston-Salem", "Fayetteville", "Cary", "Wilmington", "High Point", "Concord", "Greenville", "Asheville", "Gastonia", "Jacksonville"]},
      {"name": "Michigan", "cities": ["Detroit", "Grand Rapids", "Warren", "Sterling Heights", "Ann Arbor", "Lansing", "Flint", "Dearborn", "Livonia", "Clinton", "Troy", "Canton", "Westland", "Farmington Hills"]},
      {"name": "New Jersey", "cities": ["Newark", "Jersey City", "Paterson", "Elizabeth", "Edison", "Woodbridge", "Lakewood", "Toms River", "Hamilton", "Trenton", "Clifton", "Camden", "Brick", "Passaic"]},
      {"name": "Virginia", "cities": ["Virginia Beach", "Norfolk", "Chesapeake", "Richmond", "Newport News", "Alexandria", "Hampton", "Roanoke", "Portsmouth", "Suffolk", "Lynchburg", "Charlottesville", "Harrisonburg"]},
      {"name": "Washington", "cities": ["Seattle", "Spokane", "Tacoma", "Vancouver", "Bellevue", "Kent", "Everett", "Renton", "Federal Way", "Yakima", "Bellingham", "Kirkland", "Kennewick", "Auburn"]},
      {"name": "Arizona", "cities": ["Phoenix", "Tucson", "Mesa", "Chandler", "Scottsdale", "Glendale", "Gilbert", "Tempe", "Peoria", "Surprise", "Yuma", "Avondale", "Goodyear", "Flagstaff"]},
      {"name": "Massachusetts", "cities": ["Boston", "Worcester", "Springfield", "Cambridge", "Lowell", "Brockton", "New Bedford", "Quincy", "Lynn", "Fall River", "Newton", "Lawrence", "Somerville", "Framingham"]},
      {"name": "Tennessee", "cities": ["Memphis", "Nashville", "Knoxville", "Chattanooga", "Clarksville", "Murfreesboro", "Franklin", "Jackson", "Johnson City", "Bartlett", "Hendersonville", "Kingsport"]},
      {"name": "Indiana", "cities": ["Indianapolis", "Fort Wayne", "Evansville", "South Bend", "Carmel", "Bloomington", "Fishers", "Hammond", "Gary", "Muncie", "Lafayette", "Terre Haute", "Kokomo"]},
      {"name": "Missouri", "cities": ["Kansas City", "St. Louis", "Springfield", "Columbia", "Independence", "Lee's Summit", "O'Fallon", "St. Joseph", "St. Charles", "St. Peters", "Blue Springs", "Florissant"]},
      {"name": "Maryland", "cities": ["Baltimore", "Columbia", "Germantown", "Silver Spring", "Waldorf", "Frederick", "Ellicott City", "Glen Burnie", "Gaithersburg", "Rockville", "Bethesda", "Dundalk"]},
      {"name": "Wisconsin", "cities": ["Milwaukee", "Madison", "Green Bay", "Kenosha", "Racine", "Appleton", "Waukesha", "Oshkosh", "Eau Claire", "Janesville", "West Allis", "La Crosse", "Sheboygan"]},
      {"name": "Colorado", "cities": ["Denver", "Colorado Springs", "Aurora", "Fort Collins", "Lakewood", "Thornton", "Arvada", "Westminster", "Pueblo", "Centennial", "Boulder", "Greeley", "Longmont"]}
    ],
    "VN": [
      {"name": "Ho Chi Minh City", "cities": ["Ho Chi Minh City", "District 1", "District 3", "District 7", "Binh Thanh", "Thu Duc", "Phu Nhuan", "Go Vap", "Tan Binh", "Tan Phu", "Binh Tan"]},
      {"name": "Hanoi", "cities": ["Hanoi", "Ba Dinh", "Hoan Kiem", "Dong Da", "Hai Ba Trung", "Cau Giay", "Tay Ho", "Long Bien", "Hoang Mai", "Thanh Xuan", "Ha Dong"]},
      {"name": "Da Nang", "cities": ["Da Nang", "Hai Chau", "Thanh Khe", "Son Tra", "Ngu Hanh Son", "Lien Chieu", "Cam Le"]},
      {"name": "Hai Phong", "cities": ["Hai Phong", "Hong Bang", "Le Chan", "Kien An", "Do Son", "Duong Kinh", "Ngo Quyen"]},
      {"name": "Can Tho", "cities": ["Can Tho", "Ninh Kieu", "Binh Thuy", "Cai Rang", "O Mon", "Thot Not"]},
      {"name": "Binh Duong", "cities": ["Thu Dau Mot", "Di An", "Thuan An", "Ben Cat", "Tan Uyen", "Dau Tieng"]},
      {"name": "Dong Nai", "cities": ["Bien Hoa", "Long Thanh", "Nhon Trach", "Vinh Cuu", "Trang Bom", "Long Khanh"]},
      {"name": "Khanh Hoa", "cities": ["Nha Trang", "Cam Ranh", "Ninh Hoa", "Van Ninh", "Dien Khanh"]},
      {"name": "Quang Ninh", "cities": ["Ha Long", "Mong Cai", "Cam Pha", "Uong Bi", "Dong Trieu", "Quang Yen"]},
      {"name": "Lam Dong", "cities": ["Da Lat", "Bao Loc", "Di Linh", "Duc Trong", "Don Duong"]},
      {"name": "Thua Thien Hue", "cities": ["Hue", "Phong Dien", "Huong Tra", "Phu Vang", "Phu Loc"]}
    ],
    "IT": [
      {"name": "Lombardy", "cities": ["Milan", "Bergamo", "Brescia", "Monza", "Como", "Varese", "Pavia", "Cremona", "Mantua", "Lecco", "Lodi", "Sondrio"]},
      {"name": "Lazio", "cities": ["Rome", "Latina", "Frosinone", "Viterbo", "Rieti", "Guidonia Montecelio", "Fiumicino", "Aprilia", "Pomezia", "Tivoli"]},
      {"name": "Campania", "cities": ["Naples", "Salerno", "Giugliano", "Torre del Greco", "Caserta", "Pozzuoli", "Avellino", "Benevento", "Afragola", "Portici"]},
      {"name": "Sicily", "cities": ["Palermo", "Catania", "Messina", "Syracuse", "Ragusa", "Trapani", "Agrigento", "Caltanissetta", "Modica", "Marsala"]},
      {"name": "Veneto", "cities": ["Venice", "Verona", "Padua", "Vicenza", "Treviso", "Rovigo", "Belluno", "Chioggia", "Bassano del Grappa", "San Donà di Piave"]},
      {"name": "Piedmont", "cities": ["Turin", "Novara", "Alessandria", "Asti", "Cuneo", "Vercelli", "Biella", "Verbania", "Moncalieri", "Collegno"]},
      {"name": "Emilia-Romagna", "cities": ["Bologna", "Parma", "Modena", "Reggio Emilia", "Ravenna", "Rimini", "Ferrara", "Forlì", "Piacenza", "Cesena"]},
      {"name": "Tuscany", "cities": ["Florence", "Prato", "Livorno", "Arezzo", "Pisa", "Lucca", "Pistoia", "Siena", "Grosseto", "Carrara"]},
      {"name": "Apulia", "cities": ["Bari", "Taranto", "Foggia", "Lecce", "Brindisi", "Andria", "Barletta", "Molfetta", "Altamura", "Cerignola"]},
      {"name": "Sardinia", "cities": ["Cagliari", "Sassari", "Quartu Sant'Elena", "Olbia", "Alghero", "Nuoro", "Oristano", "Carbonia"]},
      {"name": "Calabria", "cities": ["Reggio Calabria", "Catanzaro", "Cosenza", "Crotone", "Lamezia Terme", "Vibo Valentia"]}
    ],
    "NL": [
      {"name": "North Holland", "cities": ["Amsterdam", "Haarlem", "Zaanstad", "Haarlemmermeer", "Alkmaar", "Hilversum", "Amstelveen", "Purmerend", "Hoorn", "Velsen"]},
      {"name": "South Holland", "cities": ["Rotterdam", "The Hague", "Leiden", "Dordrecht", "Zoetermeer", "Delft", "Westland", "Alphen aan den Rijn", "Schiedam", "Vlaardingen", "Gouda"]},
      {"name": "Utrecht", "cities": ["Utrecht", "Amersfoort", "Nieuwegein", "Veenendaal", "Zeist", "Houten", "IJsselstein", "Woerden"]},
      {"name": "North Brabant", "cities": ["Eindhoven", "Tilburg", "Breda", "'s-Hertogenbosch", "Helmond", "Oss", "Roosendaal", "Bergen op Zoom", "Waalwijk", "Oosterhout"]},
      {"name": "Gelderland", "cities": ["Nijmegen", "Arnhem", "Apeldoorn", "Ede", "Harderwijk", "Doetinchem", "Zutphen", "Tiel", "Wageningen"]},
      {"name": "Overijssel", "cities": ["Enschede", "Zwolle", "Deventer", "Almelo", "Hengelo", "Kampen", "Oldenzaal"]},
      {"name": "Limburg", "cities": ["Maastricht", "Venlo", "Heerlen", "Sittard-Geleen", "Roermond", "Kerkrade", "Weert"]},
      {"name": "Friesland", "cities": ["Leeuwarden", "Drachten", "Sneek", "Heerenveen", "Harlingen"]},
      {"name": "Groningen", "cities": ["Groningen", "Veendam", "Hoogezand-Sappemeer", "Stadskanaal"]},
      {"name": "Flevoland", "cities": ["Almere", "Lelystad", "Dronten", "Zeewolde"]},
      {"name": "Zeeland", "cities": ["Middelburg", "Vlissingen", "Terneuzen", "Goes"]}
    ]
  }
}
